nmosreverseproxy/__init__.py
nmosreverseproxy/proxylisting.py
nmosreverseproxy/proxylistingservice.py
usr/bin/proxylisting
nmos_reverseproxy-0.4.0.dist-info/LICENSE.md
nmos_reverseproxy-0.4.0.dist-info/METADATA
nmos_reverseproxy-0.4.0.dist-info/NOTICE.md
nmos_reverseproxy-0.4.0.dist-info/WHEEL
nmos_reverseproxy-0.4.0.dist-info/top_level.txt
nmos_reverseproxy-0.4.0.dist-info/RECORD
